[
    [
        {
            "Generation": "富邦Angels",
            "En_Gen": "fubon_angels"
        },
        {
            "Name": "潔米",
            "En_Name": "Jamie",
            "Img_Path": "./img/fubon_angels/Jamie.jpg"
        },
        {
            "Name": "慈妹",
            "En_Name": "Joycee",
            "Img_Path": "./img/fubon_angels/Joycee.jpg"
        },
        {
            "Name": "檸檬",
            "En_Name": "Lemon",
            "Img_Path": "./img/fubon_angels/Lemon.jpg"
        },
        {
            "Name": "丹丹",
            "En_Name": "DanDan",
            "Img_Path": "./img/fubon_angels/DanDan.jpg"
        },
        {
            "Name": "蓁蓁",
            "En_Name": "Jennifer",
            "Img_Path": "./img/fubon_angels/Jennifer.jpg"
        },
        {
            "Name": "秀秀子",
            "En_Name": "Showshowz",
            "Img_Path": "./img/fubon_angels/Showshowz.jpg"
        },
        {
            "Name": "安娜",
            "En_Name": "Anna",
            "Img_Path": "./img/fubon_angels/Anna.jpg"
        },
        {
            "Name": "Jessy",
            "En_Name": "Jessy",
            "Img_Path": "./img/fubon_angels/Jessy.jpg"
        },
        {
            "Name": "Tiffany",
            "En_Name": "Tiffany",
            "Img_Path": "./img/fubon_angels/Tiffany.jpg"
        },
        {
            "Name": "奶昔",
            "En_Name": "Milkshake",
            "Img_Path": "./img/fubon_angels/Milkshake.jpg"
        },
        {
            "Name": "維心",
            "En_Name": "Weihsin",
            "Img_Path": "./img/fubon_angels/Weihsin.jpg"
        },
        {
            "Name": "Kesha",
            "En_Name": "Kesha",
            "Img_Path": "./img/fubon_angels/Kesha.jpg"
        },
        {
            "Name": "沁沁",
            "En_Name": "ChinChin",
            "Img_Path": "./img/fubon_angels/ChinChin.jpg"
        },
        {
            "Name": "卡洛琳",
            "En_Name": "Carolyn",
            "Img_Path": "./img/fubon_angels/Carolyn.jpg"
        },
        {
            "Name": "大頭",
            "En_Name": "Bighead",
            "Img_Path": "./img/fubon_angels/Bighead.jpg"
        },
        {
            "Name": "栗子",
            "En_Name": "Chiali",
            "Img_Path": "./img/fubon_angels/Chiali.jpg"
        },
        {
            "Name": "寶兒",
            "En_Name": "BowA",
            "Img_Path": "./img/fubon_angels/BowA.jpg"
        },
        {
            "Name": "南珉貞",
            "En_Name": "Nam_Minjeong",
            "Img_Path": "./img/fubon_angels/Nam_Minjeong.jpg"
        },
        {
            "Name": "李雅英",
            "En_Name": "Lee_Ahyeong",
            "Img_Path": "./img/fubon_angels/Lee_Ahyeong.jpg"
        },
        {
            "Name": "金渡娥",
            "En_Name": "Kim_Doa",
            "Img_Path": "./img/fubon_angels/Kim_Doa.jpg"
        },
        {
            "Name": "金子仁",
            "En_Name": "Kim_Jain",
            "Img_Path": "./img/fubon_angels/Kim_Jain.jpg"
        },
        {
            "Name": "李珠珢",
            "En_Name": "Lee_Jueun",
            "Img_Path": "./img/fubon_angels/Lee_Jueun.jpg"
        },
        {
            "Name": "禾羽",
            "En_Name": "He_Yu",
            "Img_Path": "./img/fubon_angels/He_Yu.jpg"
        },
        {
            "Name": "雅惟",
            "En_Name": "Ya_Wei",
            "Img_Path": "./img/fubon_angels/Ya_Wei.jpg"
        },
        {
            "Name": "潔潔",
            "En_Name": "JieJie",
            "Img_Path": "./img/fubon_angels/JieJie.jpg"
        },
        {
            "Name": "Kapo",
            "En_Name": "Kapo",
            "Img_Path": "./img/fubon_angels/Kapo.jpg"
        }
    ]
]